awx_plugin_credential_github/__init__.py
awx_plugin_credential_github/exceptions.py
awx_plugin_credential_github/plugin.py
awx_plugin_credential_github-1.0.0.dist-info/METADATA
awx_plugin_credential_github-1.0.0.dist-info/WHEEL
awx_plugin_credential_github-1.0.0.dist-info/entry_points.txt
awx_plugin_credential_github-1.0.0.dist-info/licenses/LICENSE
awx_plugin_credential_github-1.0.0.dist-info/RECORD
