Metadata-Version: 2.3
Name: awx-plugin-credential-github
Version: 1.0.0
Summary: A credential plugin for AWX/AAP to authenticate with a GitHub App
Project-URL: Homepage, https://github.com/irunasroot/plugin-credenital-awx-github
Project-URL: Issues, https://github.com/irunasroot/plugin-credenital-awx-github/issues
Project-URL: Documentation, https://github.com/irunasroot/plugin-credenital-awx-github/wiki
Project-URL: Repository, https://github.com/irunasroot/plugin-credenital-awx-github.git
Project-URL: Changelog, https://github.com/irunasroot/plugin-credenital-awx-github/blob/main/CHANGELOG.md
Author-email: Dennis Whitney <denniswhitney@irunasroot.com>
License:                     GNU GENERAL PUBLIC LICENSE
License-File: LICENSE
Keywords: aap,actions,ansible,awx,redhat
Classifier: License :: OSI Approved :: GNU General Public License v3 (GPLv3)
Classifier: Natural Language :: English
Classifier: Operating System :: POSIX :: Linux
Classifier: Programming Language :: Python :: 3
Requires-Python: >=3.8
Requires-Dist: pygithub
